rikibot/__init__.py
rikibot/__main__.py
rikibot/core.py
rikibot-0.1.1.dist-info/LICENSE
rikibot-0.1.1.dist-info/METADATA
rikibot-0.1.1.dist-info/WHEEL
rikibot-0.1.1.dist-info/entry_points.txt
rikibot-0.1.1.dist-info/top_level.txt
rikibot-0.1.1.dist-info/RECORD
