Metadata-Version: 2.1
Name: rikibot
Version: 0.1.1
Summary: A simple Python package named rikibot.
Home-page: https://github.com/anhvu-sg/rikibot
Author: Vu Nguyen
Author-email: anhvusg.it@gmail.com
License: MIT
Classifier: Programming Language :: Python :: 3
Classifier: License :: OSI Approved :: MIT License
Classifier: Operating System :: OS Independent
Requires-Python: >=3.10
License-File: LICENSE
